{
  "_fv": 39,
  "_type": "recipe",
  "definition": {
    "recipeType": "Crafting",
    "xpReward": 0.0,
    "cookingTime": 200,
    "recipeRetstackSize": 1,
    "group": "",
    "recipeShapeless": false,
    "recipeSlots": [
      {
        "value": ""
      },
      {
        "value": "CUSTOM:MetaCarbonite"
      },
      {
        "value": ""
      },
      {
        "value": ""
      },
      {
        "value": "CUSTOM:LunarbarkStick"
      },
      {
        "value": ""
      },
      {
        "value": ""
      },
      {
        "value": "CUSTOM:LunarbarkStick"
      },
      {
        "value": ""
      }
    ],
    "recipeReturnStack": {
      "value": "CUSTOM:MetaCarboniteShovel"
    },
    "name": "c_meta_carbonite_shovel",
    "namespace": "mod"
  }
}