{
  "_fv": 47,
  "_type": "tool",
  "definition": {
    "toolType": "Pickaxe",
    "renderType": 0,
    "texture": "nightpickaxe",
    "customModelName": "Normal",
    "name": "Nightpickaxe",
    "specialInfo": [],
    "creativeTab": {
      "value": "CUSTOM:VoidItemsAndBlocks"
    },
    "harvestLevel": 4,
    "efficiency": 9.0,
    "attackSpeed": 1.2,
    "enchantability": 22,
    "damageVsEntity": 4.0,
    "usageCount": 0,
    "blocksAffected": [],
    "hasGlow": false,
    "repairItems": [
      {
        "value": "CUSTOM:LunarbarkPlanks"
      }
    ],
    "immuneToFire": true,
    "stayInGridWhenCrafting": true,
    "damageOnCrafting": false
  }
}